liteobj/__init__.py
liteobj/lite.py
liteobj/requirements.txt
gitio_app-0.0.8.dist-info/LICENSE
gitio_app-0.0.8.dist-info/METADATA
gitio_app-0.0.8.dist-info/WHEEL
gitio_app-0.0.8.dist-info/entry_points.txt
gitio_app-0.0.8.dist-info/top_level.txt
gitio_app-0.0.8.dist-info/RECORD
